json_pretty_diff/__init__.py
json_pretty_diff/cli.py
json_pretty_diff/version.py
json_pretty_diff/application/__init__.py
json_pretty_diff/application/use_cases.py
json_pretty_diff/domain/__init__.py
json_pretty_diff/domain/models.py
json_pretty_diff/domain/services.py
json_pretty_diff/infrastructure/__init__.py
json_pretty_diff/infrastructure/cli.py
json_pretty_diff/presentation/__init__.py
json_pretty_diff/presentation/html_renderer/__init__.py
json_pretty_diff/presentation/html_renderer/_anchors.py
json_pretty_diff/presentation/html_renderer/_branding.py
json_pretty_diff/presentation/html_renderer/_diff_data.py
json_pretty_diff/presentation/html_renderer/_diff_view.py
json_pretty_diff/presentation/html_renderer/_full_json.py
json_pretty_diff/presentation/html_renderer/_full_json_script.py
json_pretty_diff/presentation/html_renderer/_page.py
json_pretty_diff/presentation/html_renderer/_summary.py
json_pretty_diff-1.0.0.dist-info/licenses/LICENSE
json_pretty_diff-1.0.0.dist-info/METADATA
json_pretty_diff-1.0.0.dist-info/WHEEL
json_pretty_diff-1.0.0.dist-info/entry_points.txt
json_pretty_diff-1.0.0.dist-info/top_level.txt
json_pretty_diff-1.0.0.dist-info/RECORD
