Metadata-Version: 2.4
Name: json-pretty-diff
Version: 1.0.0
Summary: HTML-only diff generator for top-level JSON objects
Author: Javier Lianes García
Project-URL: Homepage, https://github.com/JaviLianes8/json-pretty-diff
Project-URL: Documentation, https://github.com/JaviLianes8/json-pretty-diff#readme
Project-URL: Bug Tracker, https://github.com/JaviLianes8/json-pretty-diff/issues
Project-URL: LinkedIn, https://www.linkedin.com/in/jlianes/
Project-URL: Funding, https://buymeacoffee.com/jlianesglrs
Keywords: json,diff,html,cli,report
Classifier: Programming Language :: Python :: 3
Classifier: License :: OSI Approved :: MIT License
Classifier: Operating System :: OS Independent
Requires-Python: >=3.9
License-File: LICENSE
Dynamic: license-file
